{"cameraMode":{"drawMode":0,"name":"Shaded","section":"Shading Mode"},"sceneLighting":true,"audioPlay":false,"sceneViewState":{"m_AlwaysRefresh":false,"showFog":true,"showSkybox":true,"showFlares":true,"showImageEffects":true,"showParticleSystems":true,"showVisualEffectGraphs":true,"m_FxEnabled":true},"in2DMode":false,"pivot":{"x":-35.909027099609378,"y":42.92839431762695,"z":174.82742309570313},"rotation":{"x":0.07383765280246735,"y":-0.5058245062828064,"z":0.04351156949996948,"w":0.8583687543869019},"size":78.67279052734375,"orthographic":false}